akscmd/__init__.py
akscmd/__main__.py
akscmd/cli.py
akscmd/hooks.sh
akscmd/instruction.txt
akscmd-0.1.2.dist-info/METADATA
akscmd-0.1.2.dist-info/WHEEL
akscmd-0.1.2.dist-info/entry_points.txt
akscmd-0.1.2.dist-info/licenses/LICENSE
akscmd-0.1.2.dist-info/RECORD
