Metadata-Version: 2.4
Name: akscmd
Version: 0.1.2
Summary: Natural language → shell command using AI models, with optional <...> Enter interception
Author-email: Amit Kumar Singh <aksmlibts@gmail.com>
License: MIT
License-File: LICENSE
Requires-Python: >=3.8
Requires-Dist: requests>=2.32.3
